fds/__init__.py
fds/sdk/__init__.py
fds/sdk/TimeSeriesAPIforDigitalPortals/__init__.py
fds/sdk/TimeSeriesAPIforDigitalPortals/api_client.py
fds/sdk/TimeSeriesAPIforDigitalPortals/configuration.py
fds/sdk/TimeSeriesAPIforDigitalPortals/exceptions.py
fds/sdk/TimeSeriesAPIforDigitalPortals/model_utils.py
fds/sdk/TimeSeriesAPIforDigitalPortals/rest.py
fds/sdk/TimeSeriesAPIforDigitalPortals/api/__init__.py
fds/sdk/TimeSeriesAPIforDigitalPortals/api/prices_api.py
fds/sdk/TimeSeriesAPIforDigitalPortals/api/vendor_api.py
fds/sdk/TimeSeriesAPIforDigitalPortals/apis/__init__.py
fds/sdk/TimeSeriesAPIforDigitalPortals/model/__init__.py
fds/sdk/TimeSeriesAPIforDigitalPortals/model/attributes_member.py
fds/sdk/TimeSeriesAPIforDigitalPortals/model/cursor_based_pagination_output_object.py
fds/sdk/TimeSeriesAPIforDigitalPortals/model/cursor_based_pagination_output_object_without_total.py
fds/sdk/TimeSeriesAPIforDigitalPortals/model/error_meta_object.py
fds/sdk/TimeSeriesAPIforDigitalPortals/model/error_object.py
fds/sdk/TimeSeriesAPIforDigitalPortals/model/inline_object.py
fds/sdk/TimeSeriesAPIforDigitalPortals/model/inline_object1.py
fds/sdk/TimeSeriesAPIforDigitalPortals/model/inline_object10.py
fds/sdk/TimeSeriesAPIforDigitalPortals/model/inline_object2.py
fds/sdk/TimeSeriesAPIforDigitalPortals/model/inline_object3.py
fds/sdk/TimeSeriesAPIforDigitalPortals/model/inline_object4.py
fds/sdk/TimeSeriesAPIforDigitalPortals/model/inline_object5.py
fds/sdk/TimeSeriesAPIforDigitalPortals/model/inline_object6.py
fds/sdk/TimeSeriesAPIforDigitalPortals/model/inline_object7.py
fds/sdk/TimeSeriesAPIforDigitalPortals/model/inline_object8.py
fds/sdk/TimeSeriesAPIforDigitalPortals/model/inline_object9.py
fds/sdk/TimeSeriesAPIforDigitalPortals/model/inline_response200.py
fds/sdk/TimeSeriesAPIforDigitalPortals/model/inline_response2001.py
fds/sdk/TimeSeriesAPIforDigitalPortals/model/inline_response20010.py
fds/sdk/TimeSeriesAPIforDigitalPortals/model/inline_response20010_data.py
fds.sdk.TimeSeriesAPIforDigitalPortals-0.10.2.dist-info/LICENSE
fds.sdk.TimeSeriesAPIforDigitalPortals-0.10.2.dist-info/METADATA
fds.sdk.TimeSeriesAPIforDigitalPortals-0.10.2.dist-info/WHEEL
fds.sdk.TimeSeriesAPIforDigitalPortals-0.10.2.dist-info/top_level.txt
fds.sdk.TimeSeriesAPIforDigitalPortals-0.10.2.dist-info/RECORD
